svinsight/__init__.py
svinsight/census_variables.py
svinsight/svi.py
svinsight-1.2.dist-info/LICENSE
svinsight-1.2.dist-info/METADATA
svinsight-1.2.dist-info/WHEEL
svinsight-1.2.dist-info/RECORD
