Metadata-Version: 2.1
Name: svinsight
Version: 1.2
Summary: Create social vulnerability index
License: MIT
Author: Matthew Preisser
Author-email: mattpreisser@gmail.com
Requires-Python: >=3.10,<4.0
Classifier: License :: OSI Approved :: MIT License
Classifier: Programming Language :: Python :: 3
Classifier: Programming Language :: Python :: 3.10
Classifier: Programming Language :: Python :: 3.11
Classifier: Programming Language :: Python :: 3.12
Classifier: Programming Language :: Python :: 3.13
Requires-Dist: PyYAML (>=6.0.2)
Requires-Dist: census (>=0.8.22)
Requires-Dist: factor_analyzer (>=0.5.1)
Requires-Dist: geopandas (>=1.0.1)
Requires-Dist: matplotlib (>=3.9.2)
Requires-Dist: numpy (>=2.1)
Requires-Dist: openpyxl (>=3.1.5)
Requires-Dist: pandas (>=2.2.3)
Requires-Dist: scikit_learn (>=1.5.2)
Requires-Dist: setuptools (>=75.3)
